dataclasses_jsonschema/__init__.py
dataclasses_jsonschema/apispec.py
dataclasses_jsonschema/field_types.py
dataclasses_jsonschema/py.typed
dataclasses_jsonschema/type_defs.py
dataclasses_jsonschema/type_hints.py
dataclasses_jsonschema-2.16.0.dist-info/LICENSE
dataclasses_jsonschema-2.16.0.dist-info/METADATA
dataclasses_jsonschema-2.16.0.dist-info/WHEEL
dataclasses_jsonschema-2.16.0.dist-info/top_level.txt
dataclasses_jsonschema-2.16.0.dist-info/RECORD
