Metadata-Version: 2.1
Name: dataclasses-jsonschema
Version: 2.16.0
Summary: JSON schema generation from dataclasses
Home-page: https://github.com/s-knibbs/dataclasses-jsonschema
Author: Simon Knibbs
Author-email: simon.knibbs@gmail.com
License: MIT
Classifier: Development Status :: 4 - Beta
Classifier: Intended Audience :: Developers
Classifier: License :: OSI Approved :: MIT License
Classifier: Programming Language :: Python
Classifier: Programming Language :: Python :: 3.7
Classifier: Programming Language :: Python :: 3.8
Classifier: Programming Language :: Python :: 3.9
Classifier: Programming Language :: Python :: 3.10
Classifier: Programming Language :: Python :: 3.11
Classifier: Topic :: Software Development :: Libraries
Provides-Extra: apispec
Provides-Extra: fast-validation
Provides-Extra: fast-dateparsing
Provides-Extra: fast-uuid
Provides-Extra: test
License-File: LICENSE
